MANIFEST.in
setup.py
bin/cla
cla/__init__.py
cla/dict/__init__.py
cla/dict/hownet.py
cla/dict/test/__init__.py
cla/dict/test/test_hownet.py
cla/learn/__init__.py
cla/learn/classifier.py
cla/learn/topic.py
cla/learn/word2vec.py
cla/learn/test/__init__.py
cla/learn/test/test_classifier.py
cla/learn/test/test_topic.py
cla/learn/test/test_word2vec.py
cla/res/dict/ne.txt
cla/res/dict/nj.txt
cla/res/dict/pe.txt
cla/res/dict/pj.txt
cla/res/dict/r.txt
cla/res/dict/s.txt
cla/res/test/labeled_test.txt
cla/res/test/labeled_train.txt
cla/res/test/model.bin
cla/res/test/qq.txt
cla/res/test/sentences.txt
cla/res/test/topics.txt
cla/res/test/words.txt
cla/util/__init__.py
cla/util/util.py
cla/util/test/__init__.py
cla/util/test/test_util.py
cla_tool.egg-info/PKG-INFO
cla_tool.egg-info/SOURCES.txt
cla_tool.egg-info/dependency_links.txt
cla_tool.egg-info/requires.txt
cla_tool.egg-info/top_level.txt