Metadata-Version: 1.0
Name: cla-tool
Version: 1.1.0
Summary: Chinese language analyze tools.
Home-page: https://github.com/dickrd/cla_tool
Author: DickRD
Author-email: dickdata7@gmail.com
License: Apache License 2.0
Platform: UNKNOWN
